code_fetch/__init__.py
code_fetch/__main__.py
code_fetch-1.0.5.dist-info/LICENSE
code_fetch-1.0.5.dist-info/METADATA
code_fetch-1.0.5.dist-info/WHEEL
code_fetch-1.0.5.dist-info/top_level.txt
code_fetch-1.0.5.dist-info/RECORD
