Metadata-Version: 2.1
Name: code-fetch
Version: 1.0.5
Summary: A package to fetch single files from Github repos instead of cloning the whole thing
Home-page: https://github.com/mordy-python/code-fetch
Author: Mordy Waldo
Author-email: imky171@gmail.com
License: UNKNOWN
Project-URL: Bug Tracker, https://github.com/mordy-python/code-fetch/issues
Platform: UNKNOWN
Classifier: Programming Language :: Python :: 3
Classifier: License :: OSI Approved :: MIT License
Classifier: Operating System :: OS Independent
Requires-Python: >=3.6
License-File: LICENSE
Requires-Dist: click
Requires-Dist: requests
